tn_sdk/__init__.py
tn_sdk/core/__init__.py
tn_sdk/core/tn_api.py
tn_sdk/exceptions/__init__.py
tn_sdk/exceptions/exceptions.py
tn_sdk/tests/__init__.py
tn_sdk/tests/test_dummy_for_sonar.py
tn_sdk/tests/test_prepare_data_for_generate_solutions.py
tn_sdk/utils/__init__.py
tn_sdk/utils/constants.py
tn_sdk-0.0.2.dist-info/licenses/LICENSE
tn_sdk-0.0.2.dist-info/METADATA
tn_sdk-0.0.2.dist-info/WHEEL
tn_sdk-0.0.2.dist-info/top_level.txt
tn_sdk-0.0.2.dist-info/RECORD
