Metadata-Version: 2.4
Name: tn_sdk
Version: 0.0.2
Summary: Trip Ninja SDK
License:                                  Apache License
Requires-Python: >=3.10
License-File: LICENSE
Provides-Extra: dev
Requires-Dist: black==25.1.0; extra == "dev"
Provides-Extra: build
Requires-Dist: build; extra == "build"
Requires-Dist: twine; extra == "build"
Requires-Dist: toml; extra == "build"
Dynamic: license-file
